<?xml version="1.0" encoding="utf-8" ?>
<sqlMap namespace="cz_system_set_kc_ex"
	xmlns="http://ibatis.apache.org/mapping"
	xmlns:xsi="http://www.w3.org/2001/XMLSchema-instance">

    <alias>
        <typeAlias alias="cz_system_set_kc_ex" type="Entity.cz_system_set_kc_ex, Entity" />
    </alias>
    <parameterMaps>
        <parameterMap id="MesnacPaggingParameters" class="map">
            <parameter property="TableName" column="TableName" />
            <parameter property="ReturnFields" column="ReturnFields" />
            <parameter property="PageSize" column="PageSize" />
            <parameter property="PageIndex" column="PageIndex" />
            <parameter property="Where" column="Where" />
            <parameter property="Orderfld" column="Orderfld" />
            <parameter property="OrderType" column="OrderType" />
        </parameterMap>
        <parameterMap id="PagerShowParameters" class="map">
            <parameter property="QueryStr" column="QueryStr" />
            <parameter property="PageSize" column="PageSize" />
            <parameter property="PageCurrent" column="PageCurrent" />
            <parameter property="FdShow" column="FdShow" />
            <parameter property="FdOrder" column="FdOrder" />
            <parameter property="Rows" column="Rows" direction="Output"/>
        </parameterMap>
    </parameterMaps>
    <resultMaps>
        <!--分页结果映射，返回实体List数据 begin-->
        <resultMap id="EntityResult" class="cz_system_set_kc_ex">
            <result property="recovery_mode" column="recovery_mode"/>
            <result property="is_hideuser" column="is_hideuser"/>
            <result property="decimal_number" column="decimal_number"/>
            <result property="max_number" column="max_number"/>
            <result property="report_open_date" column="report_open_date"/>

        </resultMap>
        <resultMap id="PageEntityResult" class="map">
            <result property="PageCount" column="PageCount" />
            <result property="RecordCount" column="RecordCount" />
        </resultMap>
        <!--分页结果映射，返回实体List数据 end-->
        <!--分页结果映射，返回DataSet数据 begin-->
        <resultMap id="TableResult" class="Row">
            <result property="recovery_mode" column="recovery_mode"/>
            <result property="is_hideuser" column="is_hideuser"/>
            <result property="decimal_number" column="decimal_number"/>
            <result property="max_number" column="max_number"/>
            <result property="report_open_date" column="report_open_date"/>

        </resultMap>
        <resultMap id="PageTableResult" class="Row">
            <result property="PageCount" column="PageCount" />
            <result property="RecordCount" column="RecordCount" />
        </resultMap>
        <!--分页结果映射，返回DataSet数据 end-->
    </resultMaps>
    <statements>
        <procedure id="cz_system_set_kc_ex.GetPageDataMesnacPagging" parameterMap="MesnacPaggingParameters" resultMap="EntityResult,PageEntityResult">
            MesnacPaging
        </procedure>
        <procedure id="cz_system_set_kc_ex.GetPageDataPagerShow" parameterMap="PagerShowParameters" resultMap="EntityResult">
            PagerShow
        </procedure>
        <procedure id="cz_system_set_kc_ex.GetPageDataSet" parameterMap="MesnacPaggingParameters" resultMap="TableResult,PageTableResult">
            MesnacPaging
        </procedure>
        <select id="cz_system_set_kc_ex.GetPageDataByReader" parameterMap="MesnacPaggingParameters">
            SELECT 
            [recovery_mode],[is_hideuser],[decimal_number],[max_number],[report_open_date] 
            FROM [dbo].[cz_system_set_kc_ex]
        </select>
        <select id="cz_system_set_kc_ex.GetRowCount" parameterClass="map" resultClass="int">
            SELECT COUNT(*) FROM [dbo].[cz_system_set_kc_ex]
        </select>
		<select id="cz_system_set_kc_ex.GetRowCountByWhere" parameterClass="String" resultClass="int">
            SELECT COUNT(*) FROM [dbo].[cz_system_set_kc_ex] WHERE 1 = 1 AND ($where$)
        </select>
        <select id="cz_system_set_kc_ex.GetById" parameterClass="map" resultClass="cz_system_set_kc_ex">
            SELECT 
            [recovery_mode],[is_hideuser],[decimal_number],[max_number],[report_open_date] 
            FROM [dbo].[cz_system_set_kc_ex] WHERE ()
        </select>

        <select id="cz_system_set_kc_ex.GetListByWhere"  parameterClass="map" resultClass="cz_system_set_kc_ex">
            SELECT 
            [recovery_mode],[is_hideuser],[decimal_number],[max_number],[report_open_date] 
            FROM [dbo].[cz_system_set_kc_ex]
            <dynamic prepend="WHERE">
                <isNotNull property="recovery_mode" prepend="AND">
                    [recovery_mode] = #recovery_mode#
                </isNotNull>
                <isNotNull property="is_hideuser" prepend="AND">
                    [is_hideuser] = #is_hideuser#
                </isNotNull>
                <isNotNull property="decimal_number" prepend="AND">
                    [decimal_number] = #decimal_number#
                </isNotNull>
                <isNotNull property="max_number" prepend="AND">
                    [max_number] = #max_number#
                </isNotNull>
                <isNotNull property="report_open_date" prepend="AND">
                    [report_open_date] = #report_open_date#
                </isNotNull>
            </dynamic>

        </select>

		<select id="cz_system_set_kc_ex.GetListByWhereStr"  parameterClass="map" resultClass="cz_system_set_kc_ex">
            SELECT 
            [recovery_mode],[is_hideuser],[decimal_number],[max_number],[report_open_date] 
            FROM [dbo].[cz_system_set_kc_ex]
            WHERE 1 = 1 AND ($where$)
        </select>

        <select id="cz_system_set_kc_ex.GetListByWhereAndOrder"  parameterClass="map" resultClass="cz_system_set_kc_ex">
            SELECT 
            [recovery_mode],[is_hideuser],[decimal_number],[max_number],[report_open_date] 
            FROM [dbo].[cz_system_set_kc_ex]
            <dynamic prepend="WHERE">
                <isNotNull property="recovery_mode" prepend="AND">
                    [recovery_mode] = #recovery_mode#
                </isNotNull>
                <isNotNull property="is_hideuser" prepend="AND">
                    [is_hideuser] = #is_hideuser#
                </isNotNull>
                <isNotNull property="decimal_number" prepend="AND">
                    [decimal_number] = #decimal_number#
                </isNotNull>
                <isNotNull property="max_number" prepend="AND">
                    [max_number] = #max_number#
                </isNotNull>
                <isNotNull property="report_open_date" prepend="AND">
                    [report_open_date] = #report_open_date#
                </isNotNull>
            </dynamic>

            <isPropertyAvailable property="OrderBy" prepend="">
                order by $OrderBy$
            </isPropertyAvailable>
        </select>

		<select id="cz_system_set_kc_ex.GetListByWhereAndOrderStr"  parameterClass="map" resultClass="cz_system_set_kc_ex">
            SELECT 
            [recovery_mode],[is_hideuser],[decimal_number],[max_number],[report_open_date] 
            FROM [dbo].[cz_system_set_kc_ex]
            WHERE 1 = 1 AND ($where$)
            <isPropertyAvailable property="OrderBy" prepend="">
                order by $OrderBy$
            </isPropertyAvailable>
        </select>

        <select id="cz_system_set_kc_ex.GetDataSetByWhere"  parameterClass="map" resultClass="Row">
            SELECT 
            [recovery_mode],[is_hideuser],[decimal_number],[max_number],[report_open_date] 
            FROM [dbo].[cz_system_set_kc_ex]
            <dynamic prepend="WHERE">
                <isNotNull property="recovery_mode" prepend="AND">
                    [recovery_mode] = #recovery_mode#
                </isNotNull>
                <isNotNull property="is_hideuser" prepend="AND">
                    [is_hideuser] = #is_hideuser#
                </isNotNull>
                <isNotNull property="decimal_number" prepend="AND">
                    [decimal_number] = #decimal_number#
                </isNotNull>
                <isNotNull property="max_number" prepend="AND">
                    [max_number] = #max_number#
                </isNotNull>
                <isNotNull property="report_open_date" prepend="AND">
                    [report_open_date] = #report_open_date#
                </isNotNull>
            </dynamic>

        </select>

		<select id="cz_system_set_kc_ex.GetDataSetByWhereStr"  parameterClass="map" resultClass="Row">
            SELECT 
            [recovery_mode],[is_hideuser],[decimal_number],[max_number],[report_open_date] 
            FROM [dbo].[cz_system_set_kc_ex]
            WHERE 1 = 1 AND ($where$)
        </select>

        <select id="cz_system_set_kc_ex.GetDataSetByFieldsAndParams"  parameterClass="map" remapResults="true" resultClass="Row">
            SELECT
            $ColumnNames$
            FROM [dbo].[cz_system_set_kc_ex]
            <dynamic prepend="WHERE">
                <isNotNull property="recovery_mode" prepend="AND">
                    [recovery_mode] = #recovery_mode#
                </isNotNull>
                <isNotNull property="is_hideuser" prepend="AND">
                    [is_hideuser] = #is_hideuser#
                </isNotNull>
                <isNotNull property="decimal_number" prepend="AND">
                    [decimal_number] = #decimal_number#
                </isNotNull>
                <isNotNull property="max_number" prepend="AND">
                    [max_number] = #max_number#
                </isNotNull>
                <isNotNull property="report_open_date" prepend="AND">
                    [report_open_date] = #report_open_date#
                </isNotNull>
            </dynamic>

        </select>
        
        <select id="cz_system_set_kc_ex.GetAllListOrder" parameterClass="map" resultClass="cz_system_set_kc_ex">
            SELECT 
            [recovery_mode],[is_hideuser],[decimal_number],[max_number],[report_open_date] 
            FROM [dbo].[cz_system_set_kc_ex]
            <isPropertyAvailable property="OrderBy" prepend="">
                order by $OrderBy$
            </isPropertyAvailable>
        </select>

        <select id="cz_system_set_kc_ex.GetTopNListWhereOrder" parameterClass="map" resultClass="cz_system_set_kc_ex">
            SELECT 
            <isPropertyAvailable property="Top" prepend="">
            Top (#Top#)
            </isPropertyAvailable>
            [recovery_mode],[is_hideuser],[decimal_number],[max_number],[report_open_date]
            FROM [dbo].[cz_system_set_kc_ex]
            <dynamic prepend="WHERE">
                <isNotNull property="recovery_mode" prepend="AND">
                    [recovery_mode] = #recovery_mode#
                </isNotNull>
                <isNotNull property="is_hideuser" prepend="AND">
                    [is_hideuser] = #is_hideuser#
                </isNotNull>
                <isNotNull property="decimal_number" prepend="AND">
                    [decimal_number] = #decimal_number#
                </isNotNull>
                <isNotNull property="max_number" prepend="AND">
                    [max_number] = #max_number#
                </isNotNull>
                <isNotNull property="report_open_date" prepend="AND">
                    [report_open_date] = #report_open_date#
                </isNotNull>
            </dynamic>

            <isPropertyAvailable property="OrderBy" prepend="">
                order by $OrderBy$
            </isPropertyAvailable>
        </select>

		<select id="cz_system_set_kc_ex.GetTopNListWhereOrderStr" parameterClass="map" resultClass="cz_system_set_kc_ex">
            SELECT 
            <isPropertyAvailable property="Top" prepend="">
            Top (#Top#)
            </isPropertyAvailable>
            [recovery_mode],[is_hideuser],[decimal_number],[max_number],[report_open_date]
            FROM [dbo].[cz_system_set_kc_ex]
            WHERE 1 = 1 AND ($where$)
            <isPropertyAvailable property="OrderBy" prepend="">
                order by $OrderBy$
            </isPropertyAvailable>
        </select>

        <select id="cz_system_set_kc_ex.GetMaxValueByProperty"  parameterClass="map" resultClass="map">
            SELECT max($ColumnName$) FROM [dbo].[cz_system_set_kc_ex]
            <dynamic prepend="WHERE">
                <isNotNull property="recovery_mode" prepend="AND">
                    [recovery_mode] = #recovery_mode#
                </isNotNull>
                <isNotNull property="is_hideuser" prepend="AND">
                    [is_hideuser] = #is_hideuser#
                </isNotNull>
                <isNotNull property="decimal_number" prepend="AND">
                    [decimal_number] = #decimal_number#
                </isNotNull>
                <isNotNull property="max_number" prepend="AND">
                    [max_number] = #max_number#
                </isNotNull>
                <isNotNull property="report_open_date" prepend="AND">
                    [report_open_date] = #report_open_date#
                </isNotNull>
            </dynamic>

        </select>
        
        <insert id="cz_system_set_kc_ex.Insert" parameterClass="cz_system_set_kc_ex" resultClass="Int32">
            INSERT INTO [dbo].[cz_system_set_kc_ex] (
            [recovery_mode],[is_hideuser],[decimal_number],[max_number],[report_open_date]
            ) VALUES (
            #recovery_mode#,#is_hideuser#,#decimal_number#,#max_number#,#report_open_date#
            )
            SELECT @@IDENTITY
        </insert>

        <update id="cz_system_set_kc_ex.Update" parameterClass="cz_system_set_kc_ex">
            UPDATE [dbo].[cz_system_set_kc_ex] SET
            [recovery_mode] = #recovery_mode#,[is_hideuser] = #is_hideuser#,[decimal_number] = #decimal_number#,[max_number] = #max_number#,[report_open_date] = #report_open_date#
            WHERE
            ()
            SELECT @@rowcount
        </update>

		<update id="cz_system_set_kc_ex.UpdateFields" parameterClass="map">
            UPDATE [dbo].[cz_system_set_kc_ex] SET
            $FieldSetValue$
            WHERE 1 = 1 AND ($where$)
            SELECT @@rowcount
        </update>

        <delete id="cz_system_set_kc_ex.Delete" parameterClass="int32">
            DELETE FROM [dbo].[cz_system_set_kc_ex]
            WHERE
            ()
            SELECT @@rowcount
        </delete>

        <delete id="cz_system_set_kc_ex.DeleteByEntity" parameterClass="cz_system_set_kc_ex">
            DELETE FROM [dbo].[cz_system_set_kc_ex]
            WHERE
            ()
            SELECT @@rowcount
        </delete>

		<delete id="cz_system_set_kc_ex.DeleteByWhere" parameterClass="String">
            DELETE FROM [dbo].[cz_system_set_kc_ex]
            WHERE 1 = 1 AND ($where$)
            SELECT @@rowcount
        </delete>

        <statement id="cz_system_set_kc_ex.ClearData">
            truncate table [cz_system_set_kc_ex]
        </statement>
    </statements>
</sqlMap>
